LICENSE
MANIFEST.in
README.md
VERSION
setup.py
wl_version_manager/__init__.py
wl_version_manager/cli.py
wl_version_manager/version_manager.py
wl_version_manager.egg-info/PKG-INFO
wl_version_manager.egg-info/SOURCES.txt
wl_version_manager.egg-info/dependency_links.txt
wl_version_manager.egg-info/entry_points.txt
wl_version_manager.egg-info/top_level.txt