Metadata-Version: 2.1
Name: wl_version_manager
Version: 0.1.10
Summary: Simple semantic version management for Python projects
Home-page: https://github.com/watkinslabs/version_manager
Author: Chris Watkins
Author-email: chris@watkinslabs.com
License: BSD 3-Clause License
Project-URL: Bug Tracker, https://github.com/watkinslabs/version_manager/issues
Project-URL: Documentation, https://github.com/watkinslabs/version_manager
Project-URL: Source Code, https://github.com/watkinslabs/version_manager
Keywords: version,versioning,semantic,semver,build,packaging
Classifier: Development Status :: 4 - Beta
Classifier: Intended Audience :: Developers
Classifier: License :: OSI Approved :: BSD License
Classifier: Programming Language :: Python :: 3
Classifier: Programming Language :: Python :: 3.6
Classifier: Programming Language :: Python :: 3.7
Classifier: Programming Language :: Python :: 3.8
Classifier: Programming Language :: Python :: 3.9
Classifier: Programming Language :: Python :: 3.10
Classifier: Programming Language :: Python :: 3.11
Classifier: Operating System :: OS Independent
Classifier: Topic :: Software Development :: Libraries :: Python Modules
Classifier: Topic :: Software Development :: Build Tools
Classifier: Topic :: System :: Software Distribution
Requires-Python: >=3.6
License-File: LICENSE
